gandi/__init__.py
gandi/auth.py
gandi/commands/__init__.py
gandi/commands/alias.py
gandi/commands/mbox.py
gandi/commands/setup.py
gandi/console.py
gandi-0.2.4.dist-info/entry_points.txt
gandi-0.2.4.dist-info/LICENSE
gandi-0.2.4.dist-info/WHEEL
gandi-0.2.4.dist-info/METADATA
gandi-0.2.4.dist-info/RECORD
