Metadata-Version: 2.1
Name: gandi
Version: 0.2.4
Summary: Command line interface to the Gandi API
Home-page: https://git.sr.ht/~gpanders/gandi-cli
License: MIT
Author: Greg Anders
Author-email: greg@gpanders.com
Requires-Python: >=3.6,<4.0
Classifier: License :: OSI Approved :: MIT License
Classifier: Programming Language :: Python :: 3
Classifier: Programming Language :: Python :: 3.6
Classifier: Programming Language :: Python :: 3.7
Classifier: Programming Language :: Python :: 3.8
Classifier: Programming Language :: Python :: 3.9
Requires-Dist: requests (>=2.23.0,<3.0.0)
Project-URL: Repository, https://git.sr.ht/~gpanders/gandi-cli
